pizza/__init__.py
pizza/__main__.py
pizza/cli.py
pizza/config.py
pizza/environment.py
pizza/exceptions.py
pizza/extensions.py
pizza/find.py
pizza/generate.py
pizza/log.py
pizza/main.py
pizza/prompt.py
pizza/replay.py
pizza/repository.py
pizza/utils.py
pizza/vcs.py
pizza_vccorp-0.1.0.dist-info/METADATA
pizza_vccorp-0.1.0.dist-info/WHEEL
pizza_vccorp-0.1.0.dist-info/entry_points.txt
pizza_vccorp-0.1.0.dist-info/top_level.txt
pizza_vccorp-0.1.0.dist-info/RECORD
