Metadata-Version: 2.1
Name: pizza-vccorp
Version: 0.1.0
Summary: Package to create pizza
Author: NguyenVT
Author-email: nguyenvothanh@channelvn.net
Classifier: Programming Language :: Python :: 3
Classifier: License :: OSI Approved :: MIT License
Classifier: Operating System :: OS Independent
Requires-Python: >=3.7
Requires-Dist: binaryornot
Requires-Dist: Jinja2
Requires-Dist: click
Requires-Dist: pyyaml
Requires-Dist: jinja2-time
Requires-Dist: python-slugify
Requires-Dist: requests
